invokeai_presets_cli/__init__.py
invokeai_presets_cli/__main__.py
invokeai_presets_cli/__version__.py
invokeai_presets_cli/cli.py
invokeai_presets_cli/functions.py
invokeai_presets_cli/helpers.py
invokeai_presets_cli-1.1.0.dist-info/METADATA
invokeai_presets_cli-1.1.0.dist-info/WHEEL
invokeai_presets_cli-1.1.0.dist-info/entry_points.txt
invokeai_presets_cli-1.1.0.dist-info/licenses/LICENSE
invokeai_presets_cli-1.1.0.dist-info/RECORD
