Metadata-Version: 2.3
Name: invokeai_presets_cli
Version: 1.1.0
Summary: CLI tool for streamlining the process of installing InvokeAI preset styles
Project-URL: Repository, https://github.com/regiellis/invokeai_presets_cli
Project-URL: Documentation, https://github.com/regiellis/invokeai_presets_cli/blob/main/README.md
Project-URL: Bug Tracker, https://github.com/regiellis/invokeai_presets_cli/issues
Author-email: Regi E <regi@bynine.io>
License: Copyright 2024 Regi E Ellis
License-File: LICENSE
Keywords: ai,cli,generative-ai,invokeai
Classifier: License :: OSI Approved :: Apache Software License
Classifier: Operating System :: OS Independent
Classifier: Programming Language :: Python :: 3.10
Requires-Python: >=3.10
Requires-Dist: httpx
Requires-Dist: inquirer
Requires-Dist: packaging
Requires-Dist: pytest
Requires-Dist: python-dotenv
Requires-Dist: rich
Requires-Dist: shellingham
Requires-Dist: typer
